cin/__init__.py
cin/agent/__init__.py
cin/agent/agent.py
cin/exceptions/__init__.py
cin/exceptions/agent_error.py
cin/exceptions/tool_error.py
cin/services/__init__.py
cin/tools/__init__.py
cin/tools/tools.py
cin/utils/__init__.py
cin/utils/json_extractor.py
cin-1.0.3.dist-info/LICENSE
cin-1.0.3.dist-info/METADATA
cin-1.0.3.dist-info/WHEEL
cin-1.0.3.dist-info/top_level.txt
cin-1.0.3.dist-info/RECORD
