Metadata-Version: 2.1
Name: cin
Version: 1.0.3
Summary: A framework for creating autonomous agents with dynamic workflows.
Author-email: Christopher Buckley <cbuckley@bytelinktechnologies.com.au>
License: MIT
Project-URL: Homepage, https://github.com/bytelinkbuckley/collective-intelligence-network
Project-URL: Repository, https://github.com/bytelinkbuckley/collective-intelligence-network
Keywords: AI,autonomous agents,framework,workflow
Classifier: Programming Language :: Python :: 3
Classifier: License :: OSI Approved :: MIT License
Classifier: Operating System :: OS Independent
Requires-Python: >=3.10
License-File: LICENSE
Requires-Dist: httpx>=0.27.2
Requires-Dist: pydantic>=2.9.2
